atx_uiautomator-0.3.3.dist-info/DESCRIPTION.rst
atx_uiautomator-0.3.3.dist-info/METADATA
atx_uiautomator-0.3.3.dist-info/RECORD
atx_uiautomator-0.3.3.dist-info/WHEEL
atx_uiautomator-0.3.3.dist-info/metadata.json
atx_uiautomator-0.3.3.dist-info/pbr.json
atx_uiautomator-0.3.3.dist-info/top_level.txt
uiautomator/__init__.py
uiautomator/adb.py
uiautomator/libs/app-uiautomator-test.apk
uiautomator/libs/app-uiautomator.apk
uiautomator/libs/bundle.jar
uiautomator/libs/uiautomator-stub.jar
