Metadata-Version: 1.1
Name: atx-uiautomator
Version: 0.3.3
Summary: Python Wrapper for Android UiAutomator test tool
Home-page: https://github.com/codeskyblue/atx-uiautomator
Author: "Xiaocong He, codeskyblue"
Author-email: UNKNOWN
License: MIT
Platform: UNKNOWN
Classifier: Development Status :: 3 - Alpha
Classifier: Environment :: Console
Classifier: Intended Audience :: Developers
Classifier: Operating System :: POSIX :: Linux
Classifier: Programming Language :: Python :: 2.7
Classifier: Programming Language :: Python :: 3.2
Classifier: Programming Language :: Python :: 3.3
Classifier: Programming Language :: Python :: 3.4
Classifier: Topic :: Software Development :: Libraries :: Python Modules
Classifier: Topic :: Software Development :: Testing
